alphalib/__init__.py
alphalib/_nbdev.py
alphalib/data/__init__.py
alphalib/data/loader.py
alphalib-0.0.3.dist-info/LICENSE
alphalib-0.0.3.dist-info/METADATA
alphalib-0.0.3.dist-info/WHEEL
alphalib-0.0.3.dist-info/entry_points.txt
alphalib-0.0.3.dist-info/top_level.txt
alphalib-0.0.3.dist-info/RECORD
