Metadata-Version: 2.1
Name: alphalib
Version: 0.0.3
Summary: A library for your daily data engineering and data science routines.
Home-page: https://github.com/alpha2phi/alphalib/tree/master/
Author: alphalib
Author-email: alpha2phi@gmail.com
License: Apache Software License 2.0
Keywords: data-science data-engineering alphalib
Platform: UNKNOWN
Classifier: Development Status :: 3 - Alpha
Classifier: Intended Audience :: Developers
Classifier: License :: OSI Approved :: Apache Software License
Classifier: Natural Language :: English
Classifier: Programming Language :: Python :: 3.6
Classifier: Programming Language :: Python :: 3.7
Classifier: Programming Language :: Python :: 3.8
Requires-Python: >=3.6
Requires-Dist: sqlalchemy
Requires-Dist: pandas
Requires-Dist: psycopg2
Requires-Dist: openpyxl
Requires-Dist: pymysql
